[
  {
    "id": "64cd0a424d61febe35f12051",
    "price": 157,
    "name": "Beth Campos"
  },
  {
    "id": "64cd0a42095da56ee798229d",
    "price": 97,
    "name": "Christian Sykes"
  },
  {
    "id": "64cd0a420898e8469fa685ee",
    "price": 335,
    "name": "Vicky Ratliff"
  },
  {
    "id": "64cd0a4205f7a1bdce421389",
    "price": 300,
    "name": "Mckee Shelton"
  },
  {
    "id": "64cd0a42417efa479f7b83e7",
    "price": 186,
    "name": "Page Nixon"
  },
  {
    "id": "64cd0a426cfc13eaf8feca62",
    "price": 51,
    "name": "Ava York"
  },
  {
    "id": "64cd0a42e45027aed933bc52",
    "price": 187,
    "name": "Shauna Miranda"
  },
  {
    "id": "64cd0a42742ff923722089a5",
    "price": 351,
    "name": "Evangelina Chavez"
  },
  {
    "id": "64cd0a42d38f91a30c21c00d",
    "price": 114,
    "name": "Tania Hall"
  },
  {
    "id": "64cd0a42e89a567fb354bcaf",
    "price": 82,
    "name": "Clark Singleton"
  },
  {
    "id": "64cd0a42f96860e8cce94a71",
    "price": 393,
    "name": "Nanette Conner"
  },
  {
    "id": "64cd0a427b16f59c2de889fb",
    "price": 375,
    "name": "Charlene Hancock"
  }
]